odoo8_addon_partner_prepayment-8.0.1.0.0.99.dev22-py3.8-nspkg.pth
odoo_addons/partner_prepayment/__init__.py
odoo_addons/partner_prepayment/__openerp__.py
odoo_addons/partner_prepayment/i18n/am.po
odoo_addons/partner_prepayment/i18n/ar.po
odoo_addons/partner_prepayment/i18n/bg.po
odoo_addons/partner_prepayment/i18n/bs.po
odoo_addons/partner_prepayment/i18n/ca.po
odoo_addons/partner_prepayment/i18n/cs.po
odoo_addons/partner_prepayment/i18n/da.po
odoo_addons/partner_prepayment/i18n/de.po
odoo_addons/partner_prepayment/i18n/el_GR.po
odoo_addons/partner_prepayment/i18n/en_GB.po
odoo_addons/partner_prepayment/i18n/es.po
odoo_addons/partner_prepayment/i18n/es_CR.po
odoo_addons/partner_prepayment/i18n/es_EC.po
odoo_addons/partner_prepayment/i18n/es_ES.po
odoo_addons/partner_prepayment/i18n/es_MX.po
odoo_addons/partner_prepayment/i18n/es_VE.po
odoo_addons/partner_prepayment/i18n/et.po
odoo_addons/partner_prepayment/i18n/fi.po
odoo_addons/partner_prepayment/i18n/fr.po
odoo_addons/partner_prepayment/i18n/fr_CA.po
odoo_addons/partner_prepayment/i18n/fr_CH.po
odoo_addons/partner_prepayment/i18n/gl.po
odoo_addons/partner_prepayment/i18n/hr.po
odoo_addons/partner_prepayment/i18n/hr_HR.po
odoo_addons/partner_prepayment/i18n/hu.po
odoo_addons/partner_prepayment/i18n/id.po
odoo_addons/partner_prepayment/i18n/it.po
odoo_addons/partner_prepayment/i18n/ja.po
odoo_addons/partner_prepayment/i18n/lt.po
odoo_addons/partner_prepayment/i18n/lv.po
odoo_addons/partner_prepayment/i18n/mk.po
odoo_addons/partner_prepayment/i18n/mn.po
odoo_addons/partner_prepayment/i18n/nb.po
odoo_addons/partner_prepayment/i18n/nb_NO.po
odoo_addons/partner_prepayment/i18n/nl.po
odoo_addons/partner_prepayment/i18n/nl_BE.po
odoo_addons/partner_prepayment/i18n/nl_NL.po
odoo_addons/partner_prepayment/i18n/partner_prepayment.pot
odoo_addons/partner_prepayment/i18n/pl.po
odoo_addons/partner_prepayment/i18n/pt.po
odoo_addons/partner_prepayment/i18n/pt_BR.po
odoo_addons/partner_prepayment/i18n/pt_PT.po
odoo8_addon_partner_prepayment-8.0.1.0.0.99.dev22.dist-info/METADATA
odoo8_addon_partner_prepayment-8.0.1.0.0.99.dev22.dist-info/WHEEL
odoo8_addon_partner_prepayment-8.0.1.0.0.99.dev22.dist-info/namespace_packages.txt
odoo8_addon_partner_prepayment-8.0.1.0.0.99.dev22.dist-info/top_level.txt
odoo8_addon_partner_prepayment-8.0.1.0.0.99.dev22.dist-info/RECORD
